fastwapi/__init__.py
fastwapi/fastwapi.py
fastwapi/main.py
fastwapi-0.1.3.dist-info/LICENSE
fastwapi-0.1.3.dist-info/METADATA
fastwapi-0.1.3.dist-info/WHEEL
fastwapi-0.1.3.dist-info/top_level.txt
fastwapi-0.1.3.dist-info/RECORD
